README.md
setup.py
codigofacilito_copia_de_nolan/__init__.py
codigofacilito_copia_de_nolan/__main__.py
codigofacilito_copia_de_nolan/workshops.py
codigofacilito_copia_de_nolan.egg-info/PKG-INFO
codigofacilito_copia_de_nolan.egg-info/SOURCES.txt
codigofacilito_copia_de_nolan.egg-info/dependency_links.txt
codigofacilito_copia_de_nolan.egg-info/requires.txt
codigofacilito_copia_de_nolan.egg-info/top_level.txt