Metadata-Version: 2.1
Name: codigofacilito-copia-de-nolan
Version: 0.0.1
Summary: Consume el API de codigo facilito
Home-page: https://github.com/NolanS-OMG/copia-codigofacilito-api
Author: Nolan Scott Ashcraft Rodríguez
Author-email: nolan1scott3@gmail.com
License: MIT
Keywords: codigofacilito
Platform: UNKNOWN
Classifier: Development Status :: 3 - Alpha
Classifier: Intended Audience :: Developers
Classifier: Topic :: Software Development :: Build Tools
Classifier: License :: OSI Approved :: MIT License
Classifier: Programming Language :: Python :: 3
